cypy/__init__.py
cypy/collections.py
cypy/compat.py
cypy/data.py
cypy/encoding.py
cypy/lex.py
cypy/meta.py
cypy/graph/__init__.py
cypy/graph/abc.py
cypy/graph/store.py
technige.cypy-1.2.2.dist-info/DESCRIPTION.rst
technige.cypy-1.2.2.dist-info/METADATA
technige.cypy-1.2.2.dist-info/RECORD
technige.cypy-1.2.2.dist-info/WHEEL
technige.cypy-1.2.2.dist-info/metadata.json
technige.cypy-1.2.2.dist-info/top_level.txt
