Metadata-Version: 2.0
Name: technige.cypy
Version: 1.2.2
Summary: Cypher resource library for Python
Home-page: http://nige.tech/cypy
Author: Nigel Small <technige@nige.tech>
Author-email: cypy@nige.tech
License: Apache License, Version 2.0
Platform: UNKNOWN
Classifier: Development Status :: 5 - Production/Stable
Classifier: Intended Audience :: Developers
Classifier: License :: OSI Approved :: Apache Software License
Classifier: Operating System :: OS Independent
Classifier: Programming Language :: Python :: 2.7
Classifier: Programming Language :: Python :: 3.4
Classifier: Programming Language :: Python :: 3.5
Classifier: Programming Language :: Python :: 3.6
Classifier: Topic :: Database
Classifier: Topic :: Software Development
